oct/__init__.py
oct/__pycache__/__init__.cpython-310.pyc
oct/__pycache__/__init__.cpython-312.pyc
oct/__pycache__/py_api.cpython-310.pyc
oct/__pycache__/py_api.cpython-312.pyc
oct/_internal.abi3.so
oct/py_api.py
oct_py-0.4.1.dist-info/METADATA
oct_py-0.4.1.dist-info/WHEEL
oct_py-0.4.1.dist-info/RECORD
