Metadata-Version: 2.4
Name: oct-py
Version: 0.4.1
Requires-Python: >=3.8
